anp_protocol/__init__.py
anp_protocol-0.1.0.dist-info/METADATA
anp_protocol-0.1.0.dist-info/WHEEL
anp_protocol-0.1.0.dist-info/RECORD
