Metadata-Version: 2.1
Name: anp-protocol
Version: 0.1.0
Summary: Agent Network Protocol implementation for agent communication and interoperability
Home-page: https://agent-network-protocol.com/
License: MIT
Author: changshan
Author-email: chgaowei@gmail.com
Requires-Python: >=3.8
Classifier: License :: OSI Approved :: MIT License
Classifier: Operating System :: OS Independent
Classifier: Programming Language :: Python :: 3
Classifier: Programming Language :: Python :: 3.8
Classifier: Programming Language :: Python :: 3.9
Classifier: Programming Language :: Python :: 3.10
Classifier: Programming Language :: Python :: 3.11
Classifier: Programming Language :: Python :: 3.12
Classifier: Programming Language :: Python :: 3.13
Requires-Dist: agent-connect (>=0.3.3,<0.4.0)
Project-URL: Documentation, https://github.com/agent-network-protocol/AgentNetworkProtocol
Project-URL: Repository, https://github.com/agent-network-protocol/AgentConnect
